hotmarkup/__init__.py
hotmarkup/conenction.py
hotmarkup/file_connection.py
hotmarkup-0.1.9.dist-info/LICENSE.md
hotmarkup-0.1.9.dist-info/METADATA
hotmarkup-0.1.9.dist-info/WHEEL
hotmarkup-0.1.9.dist-info/top_level.txt
hotmarkup-0.1.9.dist-info/RECORD
