Metadata-Version: 2.1
Name: hotmarkup
Version: 0.1.9
Summary: UNKNOWN
Home-page: https://github.com/dvec/hotmarkup
Author: Anton Ugryumov
Author-email: dvecend@gmail.com
License: UNKNOWN
Platform: UNKNOWN
Classifier: Programming Language :: Python :: 3
Classifier: License :: OSI Approved :: MIT License
Classifier: Operating System :: OS Independent
Requires-Python: >=3.6
